<?xml version="1.0" encoding="UTF-8"?>
<objects serializationModel="Studio.02.02.00">
	<object class="AudioFile" id="{74076040-b8d9-4bbd-8ab6-cf1fa9d62a9d}">
		<property name="assetPath">
			<value>FinalSounds/SFX/Projektile/Sounds/Techno.mp3</value>
		</property>
		<property name="frequencyInKHz">
			<value>44.0999985</value>
		</property>
		<property name="channelCount">
			<value>2</value>
		</property>
		<property name="length">
			<value>5.093877551020408</value>
		</property>
		<relationship name="masterAssetFolder">
			<destination>{c28b199d-e213-445f-b561-e5a286ed4dad}</destination>
		</relationship>
	</object>
</objects>
